MANIFEST.in
README.md
requirements.txt
setup.py
krautmarkt/__init__.py
krautmarkt/create.py
krautmarkt/version.py
krautmarkt.egg-info/PKG-INFO
krautmarkt.egg-info/SOURCES.txt
krautmarkt.egg-info/dependency_links.txt
krautmarkt.egg-info/entry_points.txt
krautmarkt.egg-info/not-zip-safe
krautmarkt.egg-info/requires.txt
krautmarkt.egg-info/top_level.txt
krautmarkt/core/__init__.py
krautmarkt/core/models.py
krautmarkt/extensions/__init__.py
krautmarkt/extensions/save_hugo.py
krautmarkt/extensions/source_s3.py