Metadata-Version: 2.1
Name: krautmarkt
Version: 0.0.2
Summary: Your Kraut management system
Home-page: https://github.com/DataHerb/krautmarkt
Author: Lei Ma
Author-email: hi@leima.is
License: MIT
Platform: UNKNOWN
Provides-Extra: docs
